{
  "project_info": {
    "project_number": "450336270788",
    "project_id": "moonbase-ec783",
    "storage_bucket": "moonbase-ec783.firebasestorage.app"
  },
  "client": [
    {
      "client_info": {
        "mobilesdk_app_id": "1:450336270788:android:ccf189169c8ab3b0ec9c91",
        "android_client_info": {
          "package_name": "app.edison.moonbas"
        }
      },
      "oauth_client": [],
      "api_key": [
        {
          "current_key": "AIzaSyDGy_dKSXY2Bt6Bz3HzY_eoppWJ-g5AAOk"
        }
      ],
      "services": {
        "appinvite_service": {
          "other_platform_oauth_client": []
        }
      }
    }
  ],
  "configuration_version": "1"
}